git_id/__init__.py
git_id/core.py
git_id/profile.py
git_id-1.1.2.dist-info/entry_points.txt
git_id-1.1.2.dist-info/LICENSE
git_id-1.1.2.dist-info/WHEEL
git_id-1.1.2.dist-info/METADATA
git_id-1.1.2.dist-info/RECORD
